mailprep/__init__.py
mailprep/__main__.py
mailprep/cli.py
mailprep/template.svg
mailprep/__pycache__/__init__.cpython-37.pyc
mailprep/__pycache__/cli.cpython-37.pyc
mailprep-0.1.1.dist-info/LICENSE-APACHE
mailprep-0.1.1.dist-info/LICENSE-MIT
mailprep-0.1.1.dist-info/METADATA
mailprep-0.1.1.dist-info/WHEEL
mailprep-0.1.1.dist-info/eager_resources.txt
mailprep-0.1.1.dist-info/entry_points.txt
mailprep-0.1.1.dist-info/top_level.txt
mailprep-0.1.1.dist-info/RECORD
