Metadata-Version: 2.1
Name: mailprep
Version: 0.1.1
Summary: mailprep converts vCard data into physical labels from SVG templates
Home-page: https://git.sr.ht/~lucidone/mailprep
Author: NE Automation
Author-email: code@neautomation.com
Maintainer: NE Automation
Maintainer-email: code@neautomation.com
License: MIT/Apache-2.0
Platform: UNKNOWN
Classifier: Development Status :: 4 - Beta
Classifier: Intended Audience :: Developers
Classifier: License :: OSI Approved :: MIT License
Classifier: License :: OSI Approved :: Apache Software License
Classifier: Natural Language :: English
Classifier: Operating System :: OS Independent
Classifier: Programming Language :: Python :: 3.5
Classifier: Programming Language :: Python :: 3.6
Classifier: Programming Language :: Python :: 3.7
Classifier: Programming Language :: Python :: Implementation :: CPython
Classifier: Programming Language :: Python :: Implementation :: PyPy
